cox/__init__.py
cox/readers.py
cox/store.py
cox/tensorboard_view.py
cox/utils.py
cox-0.1.post3.dist-info/LICENSE.txt
cox-0.1.post3.dist-info/METADATA
cox-0.1.post3.dist-info/WHEEL
cox-0.1.post3.dist-info/entry_points.txt
cox-0.1.post3.dist-info/top_level.txt
cox-0.1.post3.dist-info/RECORD
