Metadata-Version: 2.1
Name: cox
Version: 0.1.post3
Summary: Tools for Experiment Logging
Home-page: https://github.com/MadryLab/cox
Author: Andrew Ilyas and Logan Engstrom
Author-email: ailyas@mit.edu
License: MIT
Keywords: logging tools madrylab
Platform: UNKNOWN
Classifier: Development Status :: 4 - Beta
Classifier: Intended Audience :: Developers
Classifier: Topic :: Software Development :: Build Tools
Classifier: License :: OSI Approved :: MIT License
Classifier: Programming Language :: Python :: 3
Classifier: Programming Language :: Python :: 3.5
Classifier: Programming Language :: Python :: 3.6
Requires-Dist: tqdm
Requires-Dist: grpcio
Requires-Dist: psutil
Requires-Dist: gitpython
Requires-Dist: py3nvml
